episteme/__init__.py
episteme/__main__.py
episteme/_app.py
episteme/_credentials.py
episteme/_database.py
episteme/_main.py
episteme/_manifests.py
episteme/_model.py
episteme/_utils.py
episteme/database.py
episteme-0.0.2.dist-info/METADATA
episteme-0.0.2.dist-info/WHEEL
episteme-0.0.2.dist-info/entry_points.txt
episteme-0.0.2.dist-info/top_level.txt
episteme-0.0.2.dist-info/RECORD
