Metadata-Version: 2.1
Name: episteme
Version: 0.0.2
Summary: Manifest-driven application development
Home-page: https://github.com/magusd/episteme
Author: magusd
Author-email: magusd@magusd.com
License: MIT
Classifier: License :: OSI Approved :: MIT License
Classifier: Programming Language :: Python :: 3
Classifier: Programming Language :: Python :: 3 :: Only
Classifier: Programming Language :: Python :: Implementation :: CPython
Classifier: Programming Language :: Python :: Implementation :: PyPy
Requires-Python: >=3.7
Requires-Dist: pymongo[srv]
Requires-Dist: boto3
Requires-Dist: cerberus (~=1.3)
Requires-Dist: python-ulid
